sparkpost_async/__init__.py
sparkpost_async/apps.py
sparkpost_async/email_backend.py
sparkpost_async/tasks.py
sparkpost_async/tests.py
sparkpost_async-0.2.dist-info/LICENSE
sparkpost_async-0.2.dist-info/METADATA
sparkpost_async-0.2.dist-info/WHEEL
sparkpost_async-0.2.dist-info/top_level.txt
sparkpost_async-0.2.dist-info/RECORD
