Metadata-Version: 2.1
Name: sparkpost-async
Version: 0.2
Summary: An asynchronous SparkPost email backend for Django.
Home-page: https://github.com/armandtvz/python-sparkpost-async
Author: Armandt van Zyl
Author-email: armandtvz@gmail.com
License: GPL-3.0
Platform: UNKNOWN
Classifier: Environment :: Web Environment
Classifier: Framework :: Django
Classifier: Framework :: Django :: 3.0
Classifier: Intended Audience :: Developers
Classifier: License :: OSI Approved :: GNU General Public License v3 (GPLv3)
Classifier: Operating System :: OS Independent
Classifier: Programming Language :: Python
Classifier: Programming Language :: Python :: 3
Classifier: Programming Language :: Python :: 3.8
Classifier: Programming Language :: Python :: 3 :: Only
Classifier: Topic :: Internet :: WWW/HTTP
Requires-Python: >=3.8
License-File: LICENSE
Requires-Dist: Django (>=3.0)
Requires-Dist: sparkpost
Requires-Dist: django-dramatiq
Requires-Dist: dramatiq
